petronas_common_utils/__init__.py
petronas_common_utils/java_connector.py
petronas_common_utils/gas/__init__.py
petronas_common_utils/gas/natural_gas.py
petronas_common_utils/resources/__init__.py
petronas_common_utils/resources/petronas-common-utils-1.0-all.jar
petronas_common_utils-0.0.4.dist-info/LICENSE
petronas_common_utils-0.0.4.dist-info/METADATA
petronas_common_utils-0.0.4.dist-info/WHEEL
petronas_common_utils-0.0.4.dist-info/top_level.txt
petronas_common_utils-0.0.4.dist-info/RECORD
