Metadata-Version: 2.1
Name: petronas-common-utils
Version: 0.0.4
Summary: A collection of reusable components and utilities for streamlining development across Petronas projects and submodules 
Home-page: https://github.com/MarcEscandell/petronas-common-utils
Author: Marc Escandell Mari
Author-email: marc.escandellmari@petronas.com
License: Apache License, Version 2.0
Keywords: petronas-common-utils
Platform: UNKNOWN
Requires-Python: >=3.9
License-File: LICENSE
Requires-Dist: py4j
